scalems/__init__.py
scalems/_types.py
scalems/_version.py
scalems/commands.py
scalems/compat.py
scalems/exceptions.py
scalems/execution.py
scalems/identifiers.py
scalems/invocation.py
scalems/logger.py
scalems/messages.py
scalems/py.typed
scalems/serialization.py
scalems/unique.py
scalems/call/__init__.py
scalems/call/__main__.py
scalems/context/__init__.py
scalems/file/__init__.py
scalems/local/__init__.py
scalems/local/__main__.py
scalems/local/operations.py
scalems/radical/__init__.py
scalems/radical/__main__.py
scalems/radical/runtime.py
scalems/radical/raptor/__init__.py
scalems/store/__init__.py
scalems/store/_lock.py
scalems/subprocess/__init__.py
scalems/subprocess/_subprocess.py
scalems/workflow/__init__.py
scalems/wrappers/__init__.py
scalems/wrappers/gromacs.py
scalems-0.0.0a1.dist-info/LICENSE
scalems-0.0.0a1.dist-info/METADATA
scalems-0.0.0a1.dist-info/WHEEL
scalems-0.0.0a1.dist-info/entry_points.txt
scalems-0.0.0a1.dist-info/top_level.txt
scalems-0.0.0a1.dist-info/RECORD
