Metadata-Version: 2.1
Name: scalems
Version: 0.0.0a1
Summary: Reference implementation of the SCALE-MS data flow scripting and graph execution API for molecular science computational research protocols.
Author-email: SCALE-MS team <info@scalems.org>
License: LGPL 2.1
Project-URL: Source, https://github.com/SCALE-MS/scale-ms/
Classifier: License :: OSI Approved :: GNU Lesser General Public License v2 or later (LGPLv2+)
Classifier: Programming Language :: Python :: 3
Requires-Python: >=3.9
License-File: LICENSE
Requires-Dist: dill
Requires-Dist: mpi4py
Requires-Dist: packaging
Requires-Dist: radical.pilot (>=1.20)
Provides-Extra: test
Requires-Dist: build ; extra == 'test'
Requires-Dist: packaging ; extra == 'test'
Requires-Dist: pytest (>=6.1.2) ; extra == 'test'
Requires-Dist: pytest-asyncio (>=0.14) ; extra == 'test'
Requires-Dist: pytest-env ; extra == 'test'
Requires-Dist: radical.pilot (>=1.20) ; extra == 'test'
